spotifier/__init__.py
spotifier/client.py
spotifier/oauth.py
spotifier/scopes.py
spotifier/status_codes.py
spotifier-0.1.0.dist-info/LICENSE
spotifier-0.1.0.dist-info/WHEEL
spotifier-0.1.0.dist-info/METADATA
spotifier-0.1.0.dist-info/RECORD
