Metadata-Version: 2.1
Name: spotifier
Version: 0.1.0
Summary: A Spotify Web API Library for Modern Python
Home-page: https://github.com/skmatz/spotifier
License: MIT
Keywords: Spotify
Author: Shunta Komatsu
Author-email: shuntak217@gmail.com
Requires-Python: >=3.6,<4.0
Classifier: Development Status :: 3 - Alpha
Classifier: License :: OSI Approved :: MIT License
Classifier: Programming Language :: Python :: 3
Classifier: Programming Language :: Python :: 3.6
Classifier: Programming Language :: Python :: 3.7
Classifier: Programming Language :: Python :: 3.8
Requires-Dist: mypy_extensions (>=0.4.3,<0.5.0)
Requires-Dist: requests (>=2.23.0,<3.0.0)
Project-URL: Repository, https://github.com/skmatz/spotifier
